data_wise_location_mcp_server/__init__.py
data_wise_location_mcp_server/main.py
data_wise_location_mcp_server/query.py
data_wise_location_mcp_server/test_location.py
data_wise_location_mcp_server/upload_simple.py
data_wise_location_mcp_server/data/bank_card_bin_data.duckdb
data_wise_location_mcp_server/data/id_location.duckdb
data_wise_location_mcp_server/data/ip_location.duckdb
data_wise_location_mcp_server/data/mobile_location.duckdb
data_wise_location_mcp_server-1.0.12.dist-info/METADATA
data_wise_location_mcp_server-1.0.12.dist-info/WHEEL
data_wise_location_mcp_server-1.0.12.dist-info/entry_points.txt
data_wise_location_mcp_server-1.0.12.dist-info/licenses/LICENSE
data_wise_location_mcp_server-1.0.12.dist-info/RECORD
