Metadata-Version: 2.4
Name: data-wise-location-mcp-server
Version: 1.0.12
Summary: Location MCP Server - 提供银行、身份证、IP、手机号归属地查询的 MCP 服务
Project-URL: Homepage, https://github.com/datawisecenter/location-mcp-server
Project-URL: Repository, https://github.com/datawisecenter/location-mcp-server
Project-URL: Documentation, https://github.com/datawisecenter/location-mcp-server#readme
Project-URL: Bug Tracker, https://github.com/datawisecenter/location-mcp-server/issues
Author-email: DataWiseCenter <contact@datawisecenter.com>
License: MIT
License-File: LICENSE
Keywords: attribution,bank,fastmcp,id,ip,location,mcp,mobile
Classifier: Development Status :: 5 - Production/Stable
Classifier: Intended Audience :: Developers
Classifier: License :: OSI Approved :: MIT License
Classifier: Operating System :: OS Independent
Classifier: Programming Language :: Python :: 3
Classifier: Programming Language :: Python :: 3.8
Classifier: Programming Language :: Python :: 3.9
Classifier: Programming Language :: Python :: 3.10
Classifier: Programming Language :: Python :: 3.11
Classifier: Programming Language :: Python :: 3.12
Classifier: Topic :: Internet :: WWW/HTTP :: HTTP Servers
Classifier: Topic :: Software Development :: Libraries :: Python Modules
Requires-Python: >=3.8
Requires-Dist: duckdb==1.4.3
Requires-Dist: fastmcp>=2.14.1
Provides-Extra: dev
Requires-Dist: black>=23.0.0; extra == 'dev'
Requires-Dist: isort>=5.12.0; extra == 'dev'
Requires-Dist: mypy>=1.0.0; extra == 'dev'
Requires-Dist: pytest-asyncio>=0.21.0; extra == 'dev'
Requires-Dist: pytest>=7.0.0; extra == 'dev'
